README.rst
setup.py
Torrelque.egg-info/PKG-INFO
Torrelque.egg-info/SOURCES.txt
Torrelque.egg-info/dependency_links.txt
Torrelque.egg-info/requires.txt
Torrelque.egg-info/top_level.txt
torrelque/__init__.py
torrelque/dequeue.lua
torrelque/sweep.lua
torrelque/test.py