Metadata-Version: 2.1
Name: Torrelque
Version: 0.8.0
Summary: Asynchronous Redis-backed reliable queue package
Home-page: https://heptapod.host/saajns/torrelque
Author: saaj
Author-email: mail@saaj.me
License: LGPL-3.0-only
Project-URL: Source Code, https://heptapod.host/saajns/torrelque
Project-URL: Documentation, https://saajns.heptapod.io/torrelque/
Project-URL: Release Notes, https://saajns.heptapod.io/torrelque/history.html
Keywords: python redis asynchronous job-queue work-queue
Platform: Any
Classifier: Topic :: Software Development :: Libraries
Classifier: Framework :: AsyncIO
Classifier: Programming Language :: Python :: 3
Classifier: Programming Language :: Python :: 3 :: Only
Classifier: Programming Language :: Python :: 3.9
Classifier: Programming Language :: Python :: 3.10
Classifier: Programming Language :: Python :: 3.11
Classifier: Programming Language :: Python :: 3.12
Classifier: Programming Language :: Python :: 3.13
Classifier: Programming Language :: Python :: Implementation :: CPython
Classifier: Programming Language :: Python :: Implementation :: PyPy
Classifier: Intended Audience :: Developers
Requires-Python: >= 3
Requires-Dist: redis>=5.0.1
Provides-Extra: manual
Requires-Dist: sphinx<8,>=7; extra == "manual"
Requires-Dist: sphinx-copybutton<0.6,>=0.5.2; extra == "manual"
